qqgjyx/__init__.py
qqgjyx/exceptor.py
qqgjyx/helper.py
qqgjyx/qq.py
qqgjyx/validator.py
qqgjyx/data/__init__.py
qqgjyx/data/split.py
qqgjyx/graph/__init__.py
qqgjyx/model/__init__.py
qqgjyx/visual/__init__.py
qqgjyx/visual/plotting.py
qqgjyx-0.1.5.dist-info/licenses/LICENSE
qqgjyx-0.1.5.dist-info/METADATA
qqgjyx-0.1.5.dist-info/WHEEL
qqgjyx-0.1.5.dist-info/top_level.txt
qqgjyx-0.1.5.dist-info/RECORD
