Metadata-Version: 2.4
Name: qqgjyx
Version: 0.1.5
Summary: Personal utility toolkit
Author: Jun-Tang Wang
License-Expression: MIT
Project-URL: Homepage, https://pypi.org/project/qqgjyx/
Project-URL: Repository, https://github.com/
Classifier: Programming Language :: Python :: 3
Classifier: Operating System :: OS Independent
Classifier: Programming Language :: Python :: 3 :: Only
Requires-Python: >=3.9
License-File: LICENSE
Dynamic: license-file
